{"624629955099230228": {"Blasphemous": 30, "League of Legends": 17586, "CurseForge": 35, "VALORANT": 687, "Galaxy Life": 370, "PAYDAY 2": 182, "Wallpaper Engine": 540, "Genshin Impact": 4684, "Android Studio": 2513, "Terraria": 565, "Grand Theft Auto V": 686, "Visual Studio Code": 3200, "3D Aim Trainer": 7, "Cemu": 1279, "Overwatch": 259, "My Application \u2013 MainActivity.kt [My_Application.app.main]": 703, "Hearthstone": 320, "Rocket League": 132, "Destiny 2": 82, "ManiaPlanet": 133, "Crypt of the NecroDancer": 41, "Geometry Dash": 512, "The Forest": 13, "Muse Dash": 76, "It Takes Two Friend's Pass": 93, "Minecraft": 33, "The Sims 4": 544, "PowerWash Simulator": 557, "Besiege": 3, "Counter-Strike: Global Offensive": 69, "Aseprite": 19, "Soundfall  ": 10, "Apex Legends": 308, "Assassin's Creed Odyssey": 20, "Fortnite": 125, "Forza Horizon 5": 2133, "Real Pool 3D - Poolians": 89, "Unrailed!": 328, "Realm Royale": 49, "Rockstar Games Launcher": 1, "osu!": 42, "NBA 2K21": 7, "Cuphead": 8, "No Man's Sky": 54, "Touhou 12.3: Hisoutensoku": 18, "MultiVersus": 10, "Raft": 1965, "World of Tanks": 96, "KX-Chroma": 146, "BeamNG.drive": 60, "fm": 112, "Planet Zoo": 364, "Tribes of Midgard": 20, "Minecraft - AZ Launcher": 43, "PyCharm": 58, "pycharm64": 58, "Doki Doki Literature Club": 10, "Winemaking Simulator": 20, "Before We Leave": 9, "Not Tonight": 5}, "760073968433627146": {"League of Legends": 1555, "Visual Studio Code": 891, "Android Studio": 916, "My Application \u2013 MainActivity.kt [My_Application.app.main]": 703, "Cemu": 469, "Soundfall  ": 10, "Forza Horizon 5": 659, "Unrailed!": 65, "osu!": 39, "PyCharm": 58, "pycharm64": 58, "Genshin Impact": 44}, "761905086288756737": {"Genshin Impact": 1653, "League of Legends": 10690, "World of Tanks Blitz": 448, "Visual Studio Code": 891, "Cemu": 1133, "Overwatch": 259, "Android Studio": 916, "My Application \u2013 MainActivity.kt [My_Application.app.main]": 703, "World of Tanks": 203, "For Honor": 220, "Dead by Daylight": 496, "Grand Theft Auto V": 271, "Soundfall  ": 10, "Apex Legends": 308, "Fortnite": 443, "Forza Horizon 5": 1159, "Unrailed!": 250, "osu!": 42, "Touhou 12.3: Hisoutensoku": 18, "MultiVersus": 10, "Raft": 1790, "PyCharm": 58, "pycharm64": 58, "Minecraft": 150, "VALORANT": 2}, "846460561931632671": {"Genshin Impact": 1211, "League of Legends": 4630, "Visual Studio Code": 696, "Cemu": 1096, "Android Studio": 457, "My Application \u2013 MainActivity.kt [My_Application.app.main]": 360, "Soundfall  ": 10, "Forza Horizon 5": 603, "Unrailed!": 162, "osu!": 42, "Raft": 509, "PyCharm": 58, "pycharm64": 58}, "854733488245833758": {"League of Legends": 1555, "Visual Studio Code": 891, "Android Studio": 916, "My Application \u2013 MainActivity.kt [My_Application.app.main]": 703, "Cemu": 469, "Soundfall  ": 10, "Forza Horizon 5": 659, "Unrailed!": 65, "osu!": 39, "PyCharm": 58, "pycharm64": 58, "Genshin Impact": 44}, "907558747914764318": {"The Binding of Isaac: Rebirth": 855, "Android Studio": 2513, "Genshin Impact": 2105, "League of Legends": 3147, "Visual Studio Code": 891, "My Application \u2013 MainActivity.kt [My_Application.app.main]": 703, "Rocket League": 8, "Destiny 2": 82, "Hearthstone": 226, "Cemu": 615, "Soundfall  ": 10, "Forza Horizon 5": 1235, "Unrailed!": 143, "osu!": 39, "Geometry Dash": 10, "Raft": 175, "PyCharm": 58, "pycharm64": 58}, "908671694112182272": {"League of Legends": 1555, "Visual Studio Code": 891, "Android Studio": 916, "My Application \u2013 MainActivity.kt [My_Application.app.main]": 703, "Cemu": 469, "Soundfall  ": 10, "Forza Horizon 5": 659, "Unrailed!": 65, "osu!": 39, "PyCharm": 58, "pycharm64": 58, "Genshin Impact": 44}, "912772497760469009": {}, "976451130601132112": {"League of Legends": 3629, "F1 22 (DirectX 12)": 107, "Visual Studio Code": 891, "Erreur": 7, "Rockstar Games Launcher": 1, "Grand Theft Auto V": 64, "Android Studio": 916, "My Application \u2013 MainActivity.kt [My_Application.app.main]": 703, "Tom Clancy's Rainbow Six Siege": 48, "Rainbow Six Siege": 44, "Genshin Impact": 1306, "Cemu": 615, "FiveM": 169, "LSCITY RP": 1851, "Soundfall  ": 10, "Forza Horizon 5": 1235, "Unrailed!": 143, "osu!": 39, "TETR.IO": 92, "Raft": 175, "PyCharm": 58, "pycharm64": 58}, "988213926678380604": {"Terraria": 565, "Crypt of the NecroDancer": 41, "Genshin Impact": 99, "Planet Zoo": 364, "Tribes of Midgard": 20, "Winemaking Simulator": 20, "Before We Leave": 9, "Not Tonight": 5}, "1016790007035482193": {"Android Studio": 974, "Visual Studio Code": 195, "My Application \u2013 MainActivity.kt [My_Application.app.main]": 343, "Genshin Impact": 506, "The Binding of Isaac: Rebirth": 160, "League of Legends": 512, "VALORANT": 306, "Cemu": 37, "Forza Horizon 5": 34}}